{"id":421172683,"type":"Feature","properties":{"edtf:cessation":"uuuu","edtf:inception":"uuuu","geom:area":0,"geom:bbox":"14.59259,32.458791,14.59259,32.458791","geom:latitude":32.458791,"geom:longitude":14.59259,"iso:country":"LY","mz:note":"quattroshapes points import (201603)","qs:gn_country":null,"qs:gn_fcode":null,"qs:gn_id":null,"qs:gn_pop":null,"qs:name":"Zlitan","qs:name_adm0":"Libya","qs:name_adm1":"Zlitan","qs:photos":18,"qs:photos_1k":4,"qs:photos_9k":1,"qs:photos_9r":1,"qs:photos_all":18,"qs:photos_sr":1,"qs:placetype":"State","qs:pop_sr":0,"qs:qs_id":1317476,"qs:woe_adm0":23424882,"qs:woe_id":2346129,"src:geom":"quattroshapes","wof:belongsto":[102191573,85632627],"wof:breaches":[],"wof:concordances":{"gp:id":2346129,"qs:id":1317476},"wof:country":"LY","wof:created":1459008951,"wof:geomhash":"04b1b3ceede85cde74516590b27e2283","wof:hierarchy":[{"continent_id":102191573,"country_id":85632627,"region_id":421172683}],"wof:id":421172683,"wof:lastmodified":1459272946,"wof:name":"Zlitan","wof:parent_id":85632627,"wof:placetype":"region","wof:superseded_by":[],"wof:supersedes":[],"wof:tags":[]},"bbox":[14.59259,32.458791,14.59259,32.458791],"geometry":{"coordinates":[14.59259,32.458791],"type":"Point"}}