{"id":421194651,"type":"Feature","properties":{"edtf:cessation":"uuuu","edtf:inception":"uuuu","geom:area":0,"geom:bbox":"13.180847,32.883623,13.180847,32.883623","geom:latitude":32.883623,"geom:longitude":13.180847,"iso:country":"LY","mz:note":"quattroshapes points import (201603)","qs:gn_country":null,"qs:gn_fcode":null,"qs:gn_id":null,"qs:gn_pop":null,"qs:name":"طرابلس","qs:name_adm0":"Libya","qs:name_adm1":"Tsarrbuus","qs:photos":2745,"qs:photos_1k":556,"qs:photos_9k":24,"qs:photos_9r":14,"qs:photos_all":5460,"qs:photos_sr":18,"qs:placetype":"Town","qs:pop_sr":0,"qs:qs_id":891466,"qs:woe_adm0":23424882,"qs:woe_id":1353281,"src:geom":"quattroshapes","wof:belongsto":[102191573,85632627,85673621],"wof:breaches":[],"wof:concordances":{"gp:id":1353281,"qs:id":891466},"wof:country":"LY","wof:created":1459009815,"wof:geomhash":"f638353afedc55b9b4ebafb51ed28819","wof:hierarchy":[{"continent_id":102191573,"country_id":85632627,"locality_id":421194651,"region_id":85673621}],"wof:id":421194651,"wof:lastmodified":1459009815,"wof:name":"طرابلس","wof:parent_id":85673621,"wof:placetype":"locality","wof:superseded_by":[],"wof:supersedes":[],"wof:tags":[]},"bbox":[13.180847,32.883623,13.180847,32.883623],"geometry":{"coordinates":[13.180847,32.883623],"type":"Point"}}