{"id":421168935,"type":"Feature","properties":{"edtf:cessation":"uuuu","edtf:inception":"uuuu","geom:area":0,"geom:bbox":"15.09254,32.37535,15.09254,32.37535","geom:latitude":32.37535,"geom:longitude":15.09254,"iso:country":"LY","mz:note":"quattroshapes points import (201603)","qs:gn_country":"LY","qs:gn_fcode":"PPLA","qs:gn_id":2214846,"qs:gn_pop":386120,"qs:name":"مصراتة","qs:name_adm0":"Libya","qs:name_adm1":"مصراتة","qs:photos":386,"qs:photos_1k":78,"qs:photos_9k":2,"qs:photos_9r":5,"qs:photos_all":386,"qs:photos_sr":6,"qs:placetype":"Town","qs:pop_sr":10,"qs:qs_id":492816,"qs:woe_adm0":23424882,"qs:woe_id":1352997,"src:geom":"quattroshapes","wof:belongsto":[102191573,85632627,85673593],"wof:breaches":[],"wof:concordances":{"gn:id":2214846,"gp:id":1352997,"qs:id":492816},"wof:country":"LY","wof:created":1459008786,"wof:geomhash":"313b34113a484979bd829370cfe200d7","wof:hierarchy":[{"continent_id":102191573,"country_id":85632627,"locality_id":421168935,"region_id":85673593}],"wof:id":421168935,"wof:lastmodified":1459008786,"wof:name":"مصراتة","wof:parent_id":85673593,"wof:placetype":"locality","wof:superseded_by":[],"wof:supersedes":[],"wof:tags":[]},"bbox":[15.09254,32.37535,15.09254,32.37535],"geometry":{"coordinates":[15.09254,32.37535],"type":"Point"}}