{"id":421189687,"type":"Feature","properties":{"edtf:cessation":"uuuu","edtf:inception":"uuuu","geom:area":0,"geom:bbox":"14.289779,32.641543,14.289779,32.641543","geom:latitude":32.641543,"geom:longitude":14.289779,"iso:country":"LY","mz:note":"quattroshapes points import (201603)","qs:gn_country":null,"qs:gn_fcode":null,"qs:gn_id":null,"qs:gn_pop":null,"qs:name":"الخمس","qs:name_adm0":"Libya","qs:name_adm1":"الخمس","qs:photos":1850,"qs:photos_1k":375,"qs:photos_9k":8,"qs:photos_9r":9,"qs:photos_all":1850,"qs:photos_sr":14,"qs:placetype":"Town","qs:pop_sr":0,"qs:qs_id":1115731,"qs:woe_adm0":23424882,"qs:woe_id":1352629,"src:geom":"quattroshapes","wof:belongsto":[102191573,85632627,85673575],"wof:breaches":[],"wof:concordances":{"gp:id":1352629,"qs:id":1115731},"wof:country":"LY","wof:created":1459009633,"wof:geomhash":"8d73335fc17fe2e47559f13f3a64d88a","wof:hierarchy":[{"continent_id":102191573,"country_id":85632627,"locality_id":421189687,"region_id":85673575}],"wof:id":421189687,"wof:lastmodified":1459009633,"wof:name":"الخمس","wof:parent_id":85673575,"wof:placetype":"locality","wof:superseded_by":[],"wof:supersedes":[],"wof:tags":[]},"bbox":[14.289779,32.641543,14.289779,32.641543],"geometry":{"coordinates":[14.289779,32.641543],"type":"Point"}}