{"id":421190807,"type":"Feature","properties":{"edtf:cessation":"uuuu","edtf:inception":"uuuu","geom:area":0,"geom:bbox":"13.698921,32.432135,13.698921,32.432135","geom:latitude":32.432135,"geom:longitude":13.698921,"iso:country":"LY","mz:note":"quattroshapes points import (201603)","qs:gn_country":null,"qs:gn_fcode":null,"qs:gn_id":null,"qs:gn_pop":null,"qs:name":"Tarhunah","qs:name_adm0":"Libya","qs:name_adm1":"Tarhunah","qs:photos":5,"qs:photos_1k":1,"qs:photos_9k":1,"qs:photos_9r":1,"qs:photos_all":5,"qs:photos_sr":1,"qs:placetype":"State","qs:pop_sr":0,"qs:qs_id":1317475,"qs:woe_adm0":23424882,"qs:woe_id":2346127,"src:geom":"quattroshapes","wof:belongsto":[102191573,85632627],"wof:breaches":[],"wof:concordances":{"gp:id":2346127,"qs:id":1317475},"wof:country":"LY","wof:created":1459009669,"wof:geomhash":"73334542823b08f79b1444f22961fcbe","wof:hierarchy":[{"continent_id":102191573,"country_id":85632627,"region_id":421190807}],"wof:id":421190807,"wof:lastmodified":1459272961,"wof:name":"Tarhunah","wof:parent_id":85632627,"wof:placetype":"region","wof:superseded_by":[],"wof:supersedes":[],"wof:tags":[]},"bbox":[13.698921,32.432135,13.698921,32.432135],"geometry":{"coordinates":[13.698921,32.432135],"type":"Point"}}