{"id":421186127,"type":"Feature","properties":{"edtf:cessation":"uuuu","edtf:inception":"uuuu","geom:area":0,"geom:bbox":"20.11564,32.08456,20.11564,32.08456","geom:latitude":32.08456,"geom:longitude":20.11564,"iso:country":"LY","mz:note":"quattroshapes points import (201603)","qs:gn_country":"LY","qs:gn_fcode":"PPLX","qs:gn_id":89027,"qs:gn_pop":0,"qs:name":"Al Fuwayhåt","qs:name_adm0":"Libya","qs:name_adm1":"Banghazi","qs:photos":2,"qs:photos_1k":1,"qs:photos_9k":1,"qs:photos_9r":1,"qs:photos_all":2,"qs:photos_sr":1,"qs:placetype":"Suburb","qs:pop_sr":0,"qs:qs_id":911440,"qs:woe_adm0":23424882,"qs:woe_id":1352586,"src:geom":"quattroshapes","wof:belongsto":[],"wof:breaches":[],"wof:concordances":{"gn:id":89027,"gp:id":1352586,"qs:id":911440},"wof:country":"LY","wof:created":1459009471,"wof:geomhash":"f3b6382b2912431673bb8b8a0f4fd2e5","wof:hierarchy":[],"wof:id":421186127,"wof:lastmodified":1459272923,"wof:name":"Al Fuwayhåt","wof:parent_id":-1,"wof:placetype":"neighbourhood","wof:superseded_by":[],"wof:supersedes":[],"wof:tags":[]},"bbox":[20.11564,32.08456,20.11564,32.08456],"geometry":{"coordinates":[20.11564,32.08456],"type":"Point"}}